aiorunner/__init__.py
aiorunner/py.typed
aiorunner-0.2.0.dist-info/WHEEL
aiorunner-0.2.0.dist-info/METADATA
aiorunner-0.2.0.dist-info/RECORD
