Metadata-Version: 2.3
Name: aiorunner
Version: 0.2.0
Summary: Handle signals and cleanup context
Author: Gleb Chipiga
License: MIT License
Classifier: Intended Audience :: Developers
Classifier: Programming Language :: Python
Classifier: Programming Language :: Python :: 3
Classifier: Programming Language :: Python :: 3.11
Classifier: Programming Language :: Python :: 3.12
Classifier: Programming Language :: Python :: 3.13
Classifier: License :: OSI Approved :: MIT License
Classifier: Development Status :: 3 - Alpha
Classifier: Operating System :: POSIX
Classifier: Operating System :: MacOS :: MacOS X
Classifier: Operating System :: Microsoft :: Windows
Classifier: Topic :: Internet
Classifier: Framework :: AsyncIO
Requires-Python: >=3.11, <3.14
Project-URL: Homepage, https://github.com/gleb-chipiga/aiorunner
